MANIFEST.in
setup.py
versioneer.py
pysecure/__init__.py
pysecure/_version.py
pysecure/config.py
pysecure/easy.py
pysecure/error.py
pysecure/exceptions.py
pysecure/library.py
pysecure/log_config.py
pysecure/sftp_mirror.py
pysecure/types.py
pysecure/utility.py
pysecure.egg-info/PKG-INFO
pysecure.egg-info/SOURCES.txt
pysecure.egg-info/dependency_links.txt
pysecure.egg-info/not-zip-safe
pysecure.egg-info/top_level.txt
pysecure/adapters/__init__.py
pysecure/adapters/channela.py
pysecure/adapters/sftpa.py
pysecure/adapters/ssha.py
pysecure/calls/__init__.py
pysecure/calls/channeli.py
pysecure/calls/sftpi.py
pysecure/calls/sshi.py
pysecure/constants/__init__.py
pysecure/constants/sftp.py
pysecure/constants/ssh.py