Metadata-Version: 1.1
Name: pysecure
Version: 0.11.7
Summary: A complete Python SSH/SFTP library based on libssh.
Home-page: https://github.com/dsoprea/PySecure
Author: Dustin Oprea
Author-email: myselfasunder@gmail.com
License: GPL2
Keywords: ssh sftp
Platform: UNKNOWN
Classifier: Development Status :: 3 - Alpha
Classifier: Intended Audience :: Developers
Classifier: License :: OSI Approved :: GNU General Public License v2 (GPLv2)
Classifier: Programming Language :: Python
Classifier: Programming Language :: Python :: 2
Classifier: Programming Language :: Python :: 3
Classifier: Topic :: System :: Networking
Classifier: Topic :: Software Development :: Libraries :: Python Modules
Classifier: Topic :: System :: System Shells
Classifier: Topic :: Terminals
